src/__init__.py
src/mhaptk.py
pymHapTk-1.1.0.dist-info/LICENSE.txt
pymHapTk-1.1.0.dist-info/METADATA
pymHapTk-1.1.0.dist-info/WHEEL
pymHapTk-1.1.0.dist-info/entry_points.txt
pymHapTk-1.1.0.dist-info/top_level.txt
pymHapTk-1.1.0.dist-info/RECORD
